flask_static_digest/__init__.py
flask_static_digest/cli.py
flask_static_digest/digester.py
Flask_Static_Digest-0.4.1.dist-info/LICENSE
Flask_Static_Digest-0.4.1.dist-info/METADATA
Flask_Static_Digest-0.4.1.dist-info/WHEEL
Flask_Static_Digest-0.4.1.dist-info/entry_points.txt
Flask_Static_Digest-0.4.1.dist-info/top_level.txt
Flask_Static_Digest-0.4.1.dist-info/RECORD
