Metadata-Version: 2.1
Name: Flask-Static-Digest
Version: 0.4.1
Summary: Flask extension for md5 tagging and compressing (gzip / brotli) static files.
Home-page: https://github.com/nickjj/flask-static-digest
Author: Nick Janetakis
Author-email: nick.janetakis@gmail.com
License: MIT
Platform: any
Classifier: Environment :: Web Environment
Classifier: Framework :: Flask
Classifier: Intended Audience :: Developers
Classifier: License :: OSI Approved :: MIT License
Classifier: Operating System :: OS Independent
Classifier: Programming Language :: Python
Classifier: Programming Language :: Python :: 3
Classifier: Topic :: Internet :: WWW/HTTP :: Dynamic Content
Classifier: Topic :: Software Development :: Libraries :: Python Modules
Classifier: Topic :: System :: Archiving :: Compression
Requires-Python: >=3.6
License-File: LICENSE
Requires-Dist: Flask>=1.0
Provides-Extra: brotli
Requires-Dist: Brotli>=1.0.9; extra == "brotli"
